glytrait/__init__.py
glytrait/cli.py
glytrait/exception.py
glytrait/glycan.py
glytrait/io.py
glytrait/trait.py
glytrait/trait_forluma.txt
glytrait/trait_formula_template.txt
glytrait-0.2.3.dist-info/METADATA
glytrait-0.2.3.dist-info/WHEEL
glytrait-0.2.3.dist-info/entry_points.txt
glytrait-0.2.3.dist-info/RECORD
