Metadata-Version: 2.1
Name: glytrait
Version: 0.2.3
Summary: 
Author: fubin1999
Author-email: 65430559+fubin1999@users.noreply.github.com
Requires-Python: >=3.10,<4.0
Classifier: Programming Language :: Python :: 3
Classifier: Programming Language :: Python :: 3.10
Classifier: Programming Language :: Python :: 3.11
Requires-Dist: attrs (>=23.1.0,<24.0.0)
Requires-Dist: click (>=8.1.3,<9.0.0)
Requires-Dist: emoji (>=2.4.0,<3.0.0)
Requires-Dist: glypy (>=1.0.9,<2.0.0)
Requires-Dist: numpy (>=1.24.3,<2.0.0)
Requires-Dist: openpyxl (>=3.1.2,<4.0.0)
Requires-Dist: pandas (>=2.0.1,<3.0.0)
